synth_env/__init__.py
synth_env/environment/__init__.py
synth_env/environment/artifacts/__init__.py
synth_env/environment/artifacts/base.py
synth_env/environment/core.py
synth_env/environment/db/__init__.py
synth_env/environment/db/sqlite.py
synth_env/environment/registry.py
synth_env/environment/resources/sqlite.py
synth_env/environment/results.py
synth_env/environment/rewards/__init__.py
synth_env/environment/rewards/core.py
synth_env/environment/shared_engine.py
synth_env/environment/tools/__init__.py
synth_env/examples/__init__.py
synth_env/examples/algotune/__init__.py
synth_env/examples/algotune/agent_demos/README.md
synth_env/examples/algotune/agent_demos/algotune_basic_demo.py
synth_env/examples/algotune/agent_demos/algotune_react_agent.py
synth_env/examples/algotune/algotune_repo/.env
synth_env/examples/algotune/algotune_repo/.git/HEAD
synth_env/examples/algotune/algotune_repo/.git/config
synth_env/examples/algotune/algotune_repo/.git/description
synth_env/examples/algotune/algotune_repo/.git/hooks/applypatch-msg.sample
synth_env/examples/algotune/algotune_repo/.git/hooks/commit-msg.sample
synth_env/examples/algotune/algotune_repo/.git/hooks/fsmonitor-watchman.sample
synth_env/examples/algotune/algotune_repo/.git/hooks/post-update.sample
synth_env/examples/algotune/algotune_repo/.git/hooks/pre-applypatch.sample
synth_env/examples/algotune/algotune_repo/.git/hooks/pre-commit.sample
synth_env/examples/algotune/algotune_repo/.git/hooks/pre-merge-commit.sample
synth_env/examples/algotune/algotune_repo/.git/hooks/pre-push.sample
synth_env/examples/algotune/algotune_repo/.git/hooks/pre-rebase.sample
synth_env/examples/algotune/algotune_repo/.git/hooks/pre-receive.sample
synth_env/examples/algotune/algotune_repo/.git/hooks/prepare-commit-msg.sample
synth_env/examples/algotune/algotune_repo/.git/hooks/push-to-checkout.sample
synth_env/examples/algotune/algotune_repo/.git/hooks/update.sample
synth_env/examples/algotune/algotune_repo/.git/index
synth_env-0.1.0.dist-info/WHEEL
synth_env-0.1.0.dist-info/METADATA
synth_env-0.1.0.dist-info/RECORD
