Metadata-Version: 2.3
Name: synth-env
Version: 0.1.0
Summary: 
Author: Synth AI
Author-email: Synth AI <josh@usesynth.ai>
License: MIT
Requires-Dist: pydantic
Requires-Dist: python-dotenv>=1.0.1
Requires-Dist: pytest>=8.3.3
Requires-Dist: pydantic-openapi-schema>=1.5.1
Requires-Dist: pytest-asyncio>=0.24.0
Requires-Dist: numpy>=2.2.3
Requires-Dist: networkx>=3.4.2
Requires-Dist: synth-ai
Requires-Dist: synth-sdk
Requires-Dist: crafter>=1.8.3
Requires-Dist: fastapi>=0.115.12
Requires-Dist: gym-sokoban>=0.0.6
Requires-Dist: gymnasium>=1.1.1
Requires-Dist: uvicorn>=0.34.2
Requires-Dist: ty>=0.0.1a5
Requires-Dist: ruff>=0.11.10
Requires-Dist: pyboy>=2.6.0
Requires-Dist: setuptools>=80.8.0
Requires-Dist: psutil>=7.0.0
Requires-Dist: redis>=6.2.0
Requires-Dist: imageio>=2.31.0
Requires-Dist: nle>=0.9.1
Requires-Dist: matplotlib>=3.10.3
Requires-Dist: seaborn>=0.13.2
Requires-Dist: pillow>=11.2.1
Requires-Dist: minigrid>=3.0.0
Requires-Dist: tabulate>=0.9.0
Requires-Dist: tqdm>=4.67.1
Requires-Dist: duckdb>=1.0.0
Requires-Dist: pyarrow>=18.0.0
Requires-Dist: reflex>=0.3.8
Requires-Dist: pandas>=2.2.3
Requires-Python: >=3.11
Project-URL: Homepage, https://github.com/synth-laboratories/Environments
